rubix_api/__init__.py
rubix_api/auth.py
rubix_api-1.0.0.dist-info/DESCRIPTION.rst
rubix_api-1.0.0.dist-info/METADATA
rubix_api-1.0.0.dist-info/RECORD
rubix_api-1.0.0.dist-info/WHEEL
rubix_api-1.0.0.dist-info/metadata.json
rubix_api-1.0.0.dist-info/top_level.txt
