Metadata-Version: 2.0
Name: rubix-api
Version: 1.0.0
Summary: Indoor api to interact with Rubix
Home-page: https://github.com/rubix-labs/rubix-api
Author: HasanJ
Author-email: hasan_sg@hotmail.com
License: UNKNOWN
Platform: UNKNOWN
Requires-Dist: requests
